README.md
setup.py
abuscom/connectors/__init__.py
abuscom/connectors/compass.py
abuscom/connectors/hubspot.py
abuscom/connectors/oracle.py
abuscom/connectors/planio.py
abuscom/connectors/postgres.py
abuscom_libs.egg-info/PKG-INFO
abuscom_libs.egg-info/SOURCES.txt
abuscom_libs.egg-info/dependency_links.txt
abuscom_libs.egg-info/requires.txt
abuscom_libs.egg-info/top_level.txt