Metadata-Version: 2.1
Name: abuscom-libs
Version: 0.1.4
Summary: Utility classes for airflow DAGs
Home-page: https://abuscom.com
Author: Leonhard Holzer
Author-email: leonhard.holzer@abuscom.com
License: BSD 2-clause
Classifier: Development Status :: 3 - Alpha
Classifier: Intended Audience :: Developers
Classifier: License :: Freeware
Classifier: Operating System :: POSIX :: Linux
Classifier: Programming Language :: Python :: 3.8
